tests/__init__.py
tests/test_client.py
tests/test_device.py
tests/test_real_device.py
python_sscma-1.0.dist-info/METADATA
python_sscma-1.0.dist-info/WHEEL
python_sscma-1.0.dist-info/top_level.txt
python_sscma-1.0.dist-info/RECORD
