Metadata-Version: 2.1
Name: python-sscma
Version: 1.0
Summary: A simple python package for Home Assistant to control SSCMA devices
Author: LynnL4
Author-email: lht856@foxmail.com
Classifier: License :: OSI Approved :: MIT License
Classifier: Programming Language :: Python :: 3
Classifier: Programming Language :: Python :: 3.6
Classifier: Programming Language :: Python :: 3.7
Classifier: Programming Language :: Python :: 3.8
